openleap/OpenLeap.py
openleap/__init__.py
openleap/gesture_recognition.pkl
openleap/sign_language_alphabet.pkl
openleap-0.5.6.dist-info/LICENSE
openleap-0.5.6.dist-info/METADATA
openleap-0.5.6.dist-info/WHEEL
openleap-0.5.6.dist-info/top_level.txt
openleap-0.5.6.dist-info/RECORD
