Metadata-Version: 2.1
Name: openleap
Version: 0.5.6
Summary: Hand tracking and gesture recognition module
Home-page: https://github.com/szymciem8/OpenLeap
Author: Szymon Ciemała
Author-email: szymciem@protonmail.com
License: LICENSE
Platform: UNKNOWN
Classifier: Programming Language :: Python :: 3
Classifier: License :: OSI Approved :: MIT License
Classifier: Operating System :: OS Independent
License-File: LICENSE
Requires-Dist: mediapipe (~=0.8.8)
Requires-Dist: opencv-python (~=4.5.3.56)
Requires-Dist: pandas (~=1.3.4)
